pytest_vcr.py
pytest_vcr-1.0.1.dist-info/LICENSE
pytest_vcr-1.0.1.dist-info/METADATA
pytest_vcr-1.0.1.dist-info/WHEEL
pytest_vcr-1.0.1.dist-info/entry_points.txt
pytest_vcr-1.0.1.dist-info/top_level.txt
pytest_vcr-1.0.1.dist-info/RECORD
