Metadata-Version: 2.1
Name: pytest-vcr
Version: 1.0.1
Summary: Plugin for managing VCR.py cassettes
Home-page: https://github.com/ktosiek/pytest-vcr
Author: Tomasz Kontusz
Author-email: tomasz.kontusz@gmail.com
Maintainer: Tomasz Kontusz
Maintainer-email: tomasz.kontusz@gmail.com
License: MIT
Platform: UNKNOWN
Classifier: Development Status :: 5 - Production/Stable
Classifier: Framework :: Pytest
Classifier: Intended Audience :: Developers
Classifier: Topic :: Software Development :: Testing
Classifier: Programming Language :: Python
Classifier: Programming Language :: Python :: 2
Classifier: Programming Language :: Python :: 2.7
Classifier: Programming Language :: Python :: 3
Classifier: Programming Language :: Python :: 3.4
Classifier: Programming Language :: Python :: 3.5
Classifier: Programming Language :: Python :: 3.6
Classifier: Programming Language :: Python :: 3.7
Classifier: Programming Language :: Python :: Implementation :: CPython
Classifier: Programming Language :: Python :: Implementation :: PyPy
Classifier: Operating System :: OS Independent
Classifier: License :: OSI Approved :: MIT License
Requires-Dist: pytest (>=3.6.0)
Requires-Dist: vcrpy
